MANIFEST.in
README.rst
VERSION
config.yaml
setup.py
guillotina_authentication/__init__.py
guillotina_authentication/api.py
guillotina_authentication/exceptions.py
guillotina_authentication/identifier.py
guillotina_authentication/user.py
guillotina_authentication/utils.py
guillotina_authentication.egg-info/PKG-INFO
guillotina_authentication.egg-info/SOURCES.txt
guillotina_authentication.egg-info/dependency_links.txt
guillotina_authentication.egg-info/requires.txt
guillotina_authentication.egg-info/top_level.txt
guillotina_authentication/tests/__init__.py
guillotina_authentication/tests/conftest.py
guillotina_authentication/tests/fixtures.py
guillotina_authentication/tests/test_install.py