Metadata-Version: 2.1
Name: guillotina-authentication
Version: 5.0.1
Summary: Authenticate Guillotina with various providers
Home-page: UNKNOWN
Author: Nathan Van Gheem
Author-email: vangheem@gmail.com
License: UNKNOWN
Platform: UNKNOWN
Provides-Extra: test
